ardpy/ledm.py
ardpy/_test.py
ardpy/__init__.py
ardpy/tlcd.py
ardpy/arduno.py
ardpy/ardpy.py
ardpy-1.1.0.dist-info/WHEEL
ardpy-1.1.0.dist-info/top_level.txt
ardpy-1.1.0.dist-info/DESCRIPTION.rst
ardpy-1.1.0.dist-info/metadata.json
ardpy-1.1.0.dist-info/METADATA
ardpy-1.1.0.dist-info/RECORD
