Metadata-Version: 2.0
Name: ardpy
Version: 1.1.0
Summary: package for raspberry pi i2c communication with Arduino
Home-page: http://github.com/salesiopark/Ardpy
Author: salesiopark
Author-email: salesiopark@gmail.com
License: PSF
Keywords: arduino i2c raspberry pi
Platform: UNKNOWN
Classifier: Programming Language :: Python :: 3.4
